docs/conf.py
docs/extras/__init__.py
docs/extras/cite.py
docs/extras/generate_extensions.py
docs/extras/generate_includes.py
extras/pyterrier-flake8-ext/setup.py
extras/pyterrier-flake8-ext/pyterrier_flake8_ext/__init__.py
extras/pyterrier-flake8-ext/pyterrier_flake8_ext/java_check.py
pyterrier/__init__.py
pyterrier/_artifact.py
pyterrier/_ops.py
pyterrier/apply.py
pyterrier/apply_base.py
pyterrier/batchretrieve.py
pyterrier/cache.py
pyterrier/debug.py
pyterrier/index.py
pyterrier/inspect.py
pyterrier/io.py
pyterrier/ltr.py
pyterrier/measures.py
pyterrier/model.py
pyterrier/new.py
pyterrier/parallel.py
pyterrier/pipelines.py
pyterrier/py.typed
pyterrier/text.py
pyterrier/transformer.py
pyterrier/utils.py
pyterrier/datasets/__init__.py
pyterrier/datasets/_builtin.py
pyterrier/datasets/_core.py
pyterrier/datasets/_irds.py
pyterrier/java/__init__.py
pyterrier/java/_core.py
pyterrier/java/_utils.py
pyterrier/java/mavenresolver.py
pyterrier/terrier/__init__.py
pyterrier/terrier/_index.py
pyterrier/terrier/_metadata_adapter.py
pyterrier/terrier/_text_loader.py
pyterrier/terrier/index.py
pyterrier/terrier/index_factory.py
pyterrier/terrier/java.py
pyterrier/terrier/retriever.py
pyterrier/terrier/rewrite.py
pyterrier/terrier/stemmer.py
pyterrier/terrier/stopwords.py
pyterrier/terrier/tokeniser.py
python_terrier-0.13.2.dist-info/LICENSE.txt
python_terrier-0.13.2.dist-info/METADATA
python_terrier-0.13.2.dist-info/WHEEL
python_terrier-0.13.2.dist-info/entry_points.txt
python_terrier-0.13.2.dist-info/top_level.txt
python_terrier-0.13.2.dist-info/RECORD
