Metadata-Version: 2.1
Name: python-terrier
Version: 0.13.2
Summary: PyTerrier
Author-email: Craig Macdonald <craig.macdonald@glasgow.ac.uk>
Maintainer-email: Craig Macdonald <craig.macdonald@glasgow.ac.uk>
Project-URL: Repository, https://github.com/terrier-org/pyterrier
Project-URL: Bug Tracker, https://github.com/terrier-org/pyterrier/issues
Project-URL: Changelog, https://github.com/terrier-org/pyterrier/releases
Project-URL: CI, https://github.com/terrier-org/pyterrier/actions
Classifier: Topic :: Text Processing
Classifier: Topic :: Text Processing :: Indexing
Classifier: Programming Language :: Python :: 3
Classifier: License :: OSI Approved :: Mozilla Public License 2.0 (MPL 2.0)
Classifier: Operating System :: OS Independent
Requires-Python: >=3.8
License-File: LICENSE.txt
Requires-Dist: numpy
Requires-Dist: pandas
Requires-Dist: more-itertools
Requires-Dist: tqdm
Requires-Dist: requests
Requires-Dist: ir-datasets >=0.3.2
Requires-Dist: pyjnius >=1.4.2
Requires-Dist: deprecated
Requires-Dist: scipy
Requires-Dist: ir-measures >=0.3.1
Requires-Dist: pytrec-eval-terrier >=0.5.3
Requires-Dist: jinja2
Requires-Dist: statsmodels
Requires-Dist: dill
Requires-Dist: joblib
Requires-Dist: chest
Requires-Dist: lz4
